mathlamp/__init__.py
mathlamp/main.py
mathlamp/stdlamp/__init__.py
mathlamp/stdlamp/grammar.lark
mathlamp-1.1.0.dist-info/entry_points.txt
mathlamp-1.1.0.dist-info/LICENSE
mathlamp-1.1.0.dist-info/LICENSES/lark-LICENSE
mathlamp-1.1.0.dist-info/LICENSES/typer-LICENSE
mathlamp-1.1.0.dist-info/METADATA
mathlamp-1.1.0.dist-info/WHEEL
mathlamp-1.1.0.dist-info/RECORD
