Metadata-Version: 2.3
Name: MathLamp
Version: 1.1.0
Summary: a functional programmig language focused on math
Author: RubberSpring
Author-email: 143825964+RubberSpring@users.noreply.github.com
Requires-Python: >=3.11
Classifier: Programming Language :: Python :: 3
Classifier: Programming Language :: Python :: 3.11
Classifier: Programming Language :: Python :: 3.12
Classifier: Programming Language :: Python :: 3.13
Requires-Dist: lark (>=1.2.2,<2.0.0)
Requires-Dist: typer (>=0.15.1,<0.16.0)
